{
  "Installer": [
    {
      "InstallerUrl": "https://pdds.quark.cn/download/stfile/kkqmqokloklokmsma/QuarkCloudDrive-v2.5.53-release-pckk@other_ch-20230927180503.exe"
    }
  ],
  "Locale": [
    {
      "Locale": "zh-CN",
      "Key": "ReleaseNotes",
      "Value": "1. 十一旅游照怎么导入电脑？这个版本为你特意更新单反 SD 卡一键导入功能，插卡即可把你的旅游照存进网盘，手机随时看。\n顺便说一句，手机版相册全新升级，智能分类，自动相簿整理，非常有惊喜！\n2. PDF 页面支持批量调整顺序啦，高效 UPUP！在线阅读编辑性能也优化升级，打开 PDF 更加快速丝滑\n如果遇到体验问题，可以通过夸克 App-个人中心-设置-客服咨询反馈，或者联系：020-66824888"
    }
  ],
  "Version": "2.5.53",
  "ReleaseTime": "2023-09-28T06:21:48Z"
}
