{
  "Installer": [
    {
      "InstallerUrl": "https://portswigger-cdn.net/burp/releases/download?product=pro&version=2023.10.2.2&type=WindowsX64"
    }
  ],
  "Locale": [
    {
      "Locale": "en-US",
      "Key": "ReleaseNotes",
      "Value": "This release introduces the BChecks test tool and notes in Repeater tabs."
    },
    {
      "Key": "ReleaseNotesUrl",
      "Value": "https://portswigger.net/burp/releases/professional-community-2023-10-2-2"
    }
  ],
  "Version": "2023.10.2.2",
  "ReleaseTime": "2023-10-16T12:37:00Z"
}
