{
  "Version": "10.6.3",
  "Installer": [
    {
      "InstallerUrl": "https://download.edrawsoft.com/cbs_down/edrawmind_10.6.3_full5370.exe"
    }
  ],
  "Locale": [
    {
      "Locale": "en-US",
      "Key": "ReleaseNotes",
      "Value": "1. AI one-click multi-level mind map creation: Simply input a sentence, and the AI assistant will create a multi-level mind map.\n\n2. Pre-scenario AI creation: Provides various pre-scenario AI creation options, such as brainstorming, copywriting, SWOT analysis, etc.\n\n3. AI continuous dialogue: Turn on the continuous dialogue feature by clicking the AI robot in the lower left corner of the workspace and converse freely with the AI assistant.\n\n4. Smart annotation: After selecting a topic, choose the Smart annotation feature in the AI generated chatbot menu. The AI Assistant will analyze the content of the topic and insert an explanation as an annotation on that topic."
    }
  ],
  "RealVersion": "10.6.3.204"
}
