{
  "Installer": [
    {
      "InstallerUrl": "https://portswigger-cdn.net/burp/releases/download?product=community&version=2023.3.5&type=WindowsX64"
    }
  ],
  "Locale": [
    {
      "Locale": "en-US",
      "Key": "ReleaseNotes",
      "Value": "This release upgrades Burp's built-in browser to Chromium 112.0.5615.137/138 for Windows and 112.0.5615.137 for Mac."
    },
    {
      "Key": "ReleaseNotesUrl",
      "Value": "https://portswigger.net/burp/releases/professional-community-2023-3-5"
    }
  ],
  "Version": "2023.3.5",
  "ReleaseTime": "2023-04-21T09:15:00Z"
}
